pandasss/__init__.py
pandasss/ai.py
pandasss-0.2.dist-info/METADATA
pandasss-0.2.dist-info/WHEEL
pandasss-0.2.dist-info/top_level.txt
pandasss-0.2.dist-info/RECORD
