Metadata-Version: 2.1
Name: pandasss
Version: 0.2
Summary: A package for doing cool stuff
Author: Manav
Author-email: manav.gandhi2002@gmail.com
